anubis_solver/__init__.py
anubis_solver/solver.py
anubis_solver/utils.py
anubis_solver-0.1.1.dist-info/METADATA
anubis_solver-0.1.1.dist-info/WHEEL
anubis_solver-0.1.1.dist-info/top_level.txt
anubis_solver-0.1.1.dist-info/RECORD
